dqrxfer/__init__.py
dqrxfer/_version.py
dqrxfer/batch_upload.py
dqrxfer/dqr_ping.py
dqrxfer/dqr_upload.py
dqrxfer/utils.py
dqrxfer-0.2.6.dist-info/LICENSE
dqrxfer-0.2.6.dist-info/METADATA
dqrxfer-0.2.6.dist-info/WHEEL
dqrxfer-0.2.6.dist-info/entry_points.txt
dqrxfer-0.2.6.dist-info/top_level.txt
dqrxfer-0.2.6.dist-info/RECORD
