Metadata-Version: 2.1
Name: dqrxfer
Version: 0.2.6
Summary: Utility to transfer dqr results to Caltech cluster
Author-email: Joseph Areeda <joseph.areeda@ligo.org>
Project-URL: Bug Tracker, https://git.ligo.org/o4-dqr/dqrxfer/-/issues
Project-URL: Source Code, https://git.ligo.org/o4-dqr/dqrxfer
Classifier: Development Status :: 4 - Beta
Classifier: Intended Audience :: Science/Research
Classifier: License :: OSI Approved :: GNU General Public License v3 or later (GPLv3+)
Classifier: Natural Language :: English
Classifier: Operating System :: OS Independent
Classifier: Programming Language :: Python
Classifier: Programming Language :: Python :: 3
Classifier: Programming Language :: Python :: 3.8
Classifier: Programming Language :: Python :: 3.9
Classifier: Programming Language :: Python :: 3.10
Classifier: Programming Language :: Python :: 3.11
Classifier: Topic :: Scientific/Engineering :: Astronomy
Classifier: Topic :: Scientific/Engineering :: Physics
Requires-Python: >=3.8
License-File: LICENSE
